.gitignore
LICENSE
Pipfile
README.adoc
demo.py
setup.cfg
setup.py
tox.ini
dashing/__init__.py
dashing/dashing.py
dashing.egg-info/PKG-INFO
dashing.egg-info/SOURCES.txt
dashing.egg-info/dependency_links.txt
dashing.egg-info/not-zip-safe
dashing.egg-info/requires.txt
dashing.egg-info/top_level.txt
examples/demo.py