Metadata-Version: 1.1
Name: dashing
Version: 0.1.0
Summary: High-level terminal-based dashboard
Home-page: https://github.com/FedericoCeratto/dashing
Author: Federico Ceratto
Author-email: federico@debian.org
License: LGPL
Keywords: dashboard terminal
Platform: UNKNOWN
Classifier: Development Status :: 4 - Beta
Classifier: Environment :: Console
Classifier: Intended Audience :: Developers
Classifier: License :: OSI Approved :: GNU Lesser General Public License v3 (LGPLv3)
